asimov/__init__.py
asimov/_monkey_patch.py
asimov/account.py
asimov/constant.py
asimov/contract.py
asimov/data_type.py
asimov/error.py
asimov/evm_log.py
asimov/node.py
asimov/solc.py
asimov/template.py
asimov/transactions.py
asimov/_utils/__init__.py
asimov/_utils/common.py
asimov/_utils/encode.py
py_asimov-0.3.0.dist-info/LICENSE
py_asimov-0.3.0.dist-info/METADATA
py_asimov-0.3.0.dist-info/WHEEL
py_asimov-0.3.0.dist-info/top_level.txt
py_asimov-0.3.0.dist-info/RECORD
