Metadata-Version: 2.1
Name: py-asimov
Version: 0.3.0
Summary: sdk for asimov chain
Home-page: https://gitlab.asimov.work/asimov/asimov-python-sdk
Author: The Asimov Foundation
Author-email: ericsgy@163.com
License: MIT License
Keywords: asimov
Platform: UNKNOWN
Classifier: Development Status :: 3 - Alpha
Classifier: Intended Audience :: Developers
Classifier: License :: OSI Approved :: MIT License
Classifier: Operating System :: OS Independent
Classifier: Natural Language :: English
Classifier: Programming Language :: Python :: 3
Classifier: Programming Language :: Python :: 3.7
Classifier: Programming Language :: Python :: 3.6
Requires-Python: >=3.6, <4
Requires-Dist: fastecdsa (<2,>=1.7.4)
Requires-Dist: web3 (<5,>=4.9.0)
Requires-Dist: python-bitcointx (<2,>=1.0.1)
Requires-Dist: requests (<3,>=2.22.0)
Requires-Dist: py-solc (<4,>=3.2.0)
Provides-Extra: dev
Requires-Dist: pytest-watch (<5,>=4.2.0) ; extra == 'dev'
Requires-Dist: ipython ; extra == 'dev'
Requires-Dist: wheel ; extra == 'dev'
Requires-Dist: twine ; extra == 'dev'
Requires-Dist: bumpversion (<1,>=0.5.3) ; extra == 'dev'
Requires-Dist: pytest (<6,>=5.2.2) ; extra == 'dev'
Requires-Dist: pytest-cov (<3,>=2.8.1) ; extra == 'dev'
Requires-Dist: tox (<4,>=3.15.0) ; extra == 'dev'
Requires-Dist: Sphinx (<2,>=1.8.5) ; extra == 'dev'
Requires-Dist: sphinx-rtd-theme (<1,>=0.4.3) ; extra == 'dev'
Provides-Extra: doc
Requires-Dist: Sphinx (<2,>=1.8.5) ; extra == 'doc'
Requires-Dist: sphinx-rtd-theme (<1,>=0.4.3) ; extra == 'doc'
Provides-Extra: lint
Provides-Extra: test
Requires-Dist: pytest (<6,>=5.2.2) ; extra == 'test'
Requires-Dist: pytest-cov (<3,>=2.8.1) ; extra == 'test'
Requires-Dist: tox (<4,>=3.15.0) ; extra == 'test'
